tool_mapi/__init__.py
tool_mapi/logger.py
tool_mapi/clitools/__init__.py
tool_mapi/clitools/print_hello_worlds.py
tool_mapi/helloworld/__init__.py
tool_mapi/helloworld/helloworld.py
tool_mapi-5.0.0.dist-info/METADATA
tool_mapi-5.0.0.dist-info/WHEEL
tool_mapi-5.0.0.dist-info/top_level.txt
tool_mapi-5.0.0.dist-info/RECORD
