Metadata-Version: 2.1
Name: tool-mapi
Version: 5.0.0
Summary: tool_mapi library
Home-page: UNKNOWN
Author: UNKNOWN
Author-email: UNKNOWN
License: UNKNOWN
Platform: UNKNOWN
